cloud_requests/__init__.py
cloud_requests-1.0.1.dist-info/LICENSE
cloud_requests-1.0.1.dist-info/METADATA
cloud_requests-1.0.1.dist-info/WHEEL
cloud_requests-1.0.1.dist-info/top_level.txt
cloud_requests-1.0.1.dist-info/RECORD
