Metadata-Version: 2.1
Name: cloud-requests
Version: 1.0.1
Summary: When making a requests to Google Cloud Service, it allows you to make a simple request without complicated authentication.
Home-page: https://github.com/da-huin/cloud_requests
Author: da-huin
Author-email: dahuin000@gmail.com
License: MIT
Download-URL: https://github.com/da-huin/cloud_requests/archive/master.zip
Platform: UNKNOWN
Classifier: Programming Language :: Python :: 3
Requires-Dist: pyjwt
Requires-Dist: requests
